figuregen/__init__.py
figuregen/backend.py
figuregen/calculate.py
figuregen/commands.tikz
figuregen/commands.typ
figuregen/element_data.py
figuregen/figuregen.py
figuregen/html.py
figuregen/layout.py
figuregen/matplot_lineplot.py
figuregen/pdflatex.py
figuregen/pgf_lineplot.py
figuregen/powerpoint.py
figuregen/svg.py
figuregen/theme.pptx
figuregen/tikz.py
figuregen/typst.py
figuregen/util/__init__.py
figuregen/util/image.py
figuregen/util/jupyter.py
figuregen/util/templates.py
figuregen/util/tex.py
figuregen/util/units.py
figuregen-1.3.3.dist-info/licenses/LICENSE
figuregen-1.3.3.dist-info/METADATA
figuregen-1.3.3.dist-info/WHEEL
figuregen-1.3.3.dist-info/top_level.txt
figuregen-1.3.3.dist-info/RECORD
