Metadata-Version: 2.4
Name: figuregen
Version: 1.3.3
Summary: Figure Generator
Home-page: https://github.com/Mira-13/figure-gen
Author: Mira Niemann
Author-email: mira.niemann@gmail.com
Classifier: Programming Language :: Python :: 3
Classifier: License :: OSI Approved :: MIT License
Classifier: Operating System :: OS Independent
Requires-Python: >=3.11
License-File: LICENSE
Requires-Dist: matplotlib>=3.2.1
Requires-Dist: python-pptx
Requires-Dist: simpleimageio
Requires-Dist: texsnip>=1.1.0
Dynamic: author
Dynamic: author-email
Dynamic: classifier
Dynamic: description
Dynamic: description-content-type
Dynamic: home-page
Dynamic: license-file
Dynamic: requires-dist
Dynamic: requires-python
Dynamic: summary
